deepagents/__init__.py
deepagents/default_agent_prompt.md
deepagents/graph.py
deepagents/backends/__init__.py
deepagents/backends/composite.py
deepagents/backends/filesystem.py
deepagents/backends/protocol.py
deepagents/backends/state.py
deepagents/backends/store.py
deepagents/backends/utils.py
deepagents/middleware/__init__.py
deepagents/middleware/agent_memory.py
deepagents/middleware/filesystem.py
deepagents/middleware/patch_tool_calls.py
deepagents/middleware/resumable_shell.py
deepagents/middleware/subagents.py
deepagents_brim-0.2.5.dist-info/licenses/LICENSE
deepagents_brim-0.2.5.dist-info/METADATA
deepagents_brim-0.2.5.dist-info/WHEEL
deepagents_brim-0.2.5.dist-info/top_level.txt
deepagents_brim-0.2.5.dist-info/RECORD
