Metadata-Version: 2.4
Name: deepagents-brim
Version: 0.2.5
Summary: General purpose 'deep agent' with sub-agent spawning, todo list capabilities, and mock file system. Built on LangGraph.
License: MIT
Requires-Python: <4.0,>=3.11
License-File: LICENSE
Requires-Dist: langchain-anthropic<2.0.0,>=1.0.0
Requires-Dist: langchain<2.0.0,>=1.0.2
Requires-Dist: langchain-core<2.0.0,>=1.0.0
Requires-Dist: wcmatch
Provides-Extra: dev
Requires-Dist: pytest; extra == "dev"
Requires-Dist: pytest-cov; extra == "dev"
Requires-Dist: build; extra == "dev"
Requires-Dist: twine; extra == "dev"
Requires-Dist: langchain-openai; extra == "dev"
Dynamic: license-file
